example/__init__.py
example/scraper.py
roboparse/__init__.py
roboparse/filters.py
roboparse/parser.py
roboparse/routers.py
roboparse/schemas.py
tests/__init__.py
tests/conftest.py
tests/test_parser.py
roboparse-0.0.2.dist-info/LICENSE
roboparse-0.0.2.dist-info/METADATA
roboparse-0.0.2.dist-info/WHEEL
roboparse-0.0.2.dist-info/top_level.txt
roboparse-0.0.2.dist-info/RECORD
