Metadata-Version: 2.1
Name: roboparse
Version: 0.0.2
Summary: Roboparse HTML
Home-page: https://github.com/Toffooo/roboparser
Author: Kel0
Author-email: rozovdima123@gmail.com
License: UNKNOWN
Platform: UNKNOWN
Classifier: Programming Language :: Python :: 3
Classifier: License :: OSI Approved :: MIT License
Classifier: Operating System :: OS Independent
Requires-Python: >=3.7
License-File: LICENSE
Requires-Dist: lxml (==4.6.3)
Requires-Dist: beautifulsoup4 (==4.9.3)
